chester/__init__.py
chester/match.py
chester/openingbook.py
chester/timecontrol.py
chester/tournament.py
chester-0.3.1.dist-info/LICENSE
chester-0.3.1.dist-info/METADATA
chester-0.3.1.dist-info/WHEEL
chester-0.3.1.dist-info/top_level.txt
chester-0.3.1.dist-info/RECORD
