Metadata-Version: 2.1
Name: chester
Version: 0.3.1
Summary: Chess Engine Tester - A simple interface to play chess engines against each other, including tournaments.
Home-page: https://www.github.com/bsamseth/python-chess-engine-tester
Author: Bendik Samseth
Author-email: b.samseth@gmail.com
License: MIT
Keywords: chess engine testing match tournament chester
Platform: UNKNOWN
Classifier: Development Status :: 3 - Alpha
Classifier: Environment :: Console
Classifier: Topic :: Utilities
Classifier: Intended Audience :: Developers
Classifier: License :: OSI Approved :: MIT License
Classifier: Natural Language :: English
Classifier: Operating System :: OS Independent
Classifier: Programming Language :: Python :: 3 :: Only
Classifier: Topic :: Utilities
Requires-Dist: python-chess (>=0.26.0)
